{"0156": "Oxford",
 "0017": "Falmouth",
 "0123": "Lancaster",
 "0048": "Bath Spa",
 "0179": "Cardiff",
 "0160": "Southampton",
 "0143": "Royal Veterinary College",
 "0057": "Derby",
 "0050": "Bournemouth",
 "0024": "University of the Arts London",
 "0174": "Stirling",
 "0016": "Edge Hill",
 "0161": "Surrey",
 "0014": "St Mark and St John",
 "0118": "Essex",
 "0209": "The Liverpool Institute for Performing Arts",
 "0157": "Reading",
 "0162": "Sussex",
 "0122": "Kent",
 "0026": "Bedfordshire",
 "0114": "Cambridge",
 "0028": "Newman",
 "0068": "De Montfort",
 "0167": "Edinburgh",
 "0124": "Leeds",
 "0184": "Queen's, Belfast",
 "0064": "Leeds Beckett",
 "0107": "Edinburgh Napier",
 "0095": "Abertay Dundee",
 "0089": "Cardiff Met",
 "0081": "UWE Bristol",
 "0201": "Courtauld Institute",
 "0113": "Brunel",
 "0034": "Royal College of Music",
 "0066": "Manchester Met",
 "0030": "Ravensbourne",
 "0007": "Bishop Grosseteste",
 "0063": "Kingston",
 "0086": "South Wales (Newport)",
 "0085": "Wolverhampton",
 "0115": "City",
 "0206": "University for the Creative Arts",
 "0104": "Robert Gordon",
 "0194": "St Mary's UC, Belfast",
 "0196": "Highlands & Islands",
 "0041": "Trinity Laban Conservatoire",
 "0139": "Queen Mary",
 "0058": "East London",
 "0131": "Goldsmiths",
 "0151": "University of London",
 "0079": "Teesside",
 "0069": "Northumbria",
 "0077": "Staffordshire",
 "0054": "Gloucestershire",
 "0052": "Birmingham City",
 "0010": "Royal Central School of Speech & Drama",
 "0168": "Glasgow",
 "0056": "Coventry",
 "0074": "Portsmouth",
 "0097": "Glasgow School of Art",
 "0021": "Winchester",
 "0177": "Aberystwyth",
 "0073": "Plymouth",
 "0117": "UEA",
 "0112": "Bristol",
 "0173": "St Andrews",
 "0049": "Bolton",
 "0100": "Queen Margaret",
 "0163": "Warwick",
 "0185": "Ulster",
 "0027": "Northampton",
 "0125": "Leicester",
 "0200": "University College Birmingham",
 "0106": "Glasgow Caledonian",
 "0083": "Westminster",
 "0061": "Huddersfield",
 "0195": "Royal Agricultural University",
 "0205": "Heythrop College",
 "0182": "Royal Welsh College",
 "0032": "Rose Bruford College",
 "0158": "Salford",
 "0189": "Writtle College",
 "0137": "London School of Economics",
 "0067": "Middlesex",
 "0001": "The Open University",
 "0037": "Southampton Solent",
 "0164": "York",
 "0009": "Bucks New University",
 "0062": "Lincoln",
 "0149": "UCL",
 "0051": "Brighton",
 "0152": "Loughborough",
 "0087": "Glyndŵr",
 "0138": "London School of Hygiene and Tropical Medicine",
 "0023": "Liverpool Hope",
 "0060": "Hertfordshire",
 "0159": "Sheffield",
 "0018": "Harper Adams",
 "0116": "Durham",
 "0071": "Nottingham Trent",
 "0169": "Strathclyde",
 "0171": "Heriot-Watt",
 "0082": "Chichester",
 "0135": "London Business School",
 "0110": "Birmingham",
 "0038": "Cumbria",
 "0119": "Exeter",
 "0075": "Sheffield Hallam",
 "0172": "Dundee",
 "0031": "Roehampton",
 "0175": "SRUC",
 "0078": "Sunderland",
 "0047": "Anglia Ruskin",
 "0133": "Institute of Education",
 "0180": "Swansea",
 "0141": "Royal Holloway",
 "0003": "Royal College of Art",
 "0002": "Cranfield University",
 "0121": "Keele",
 "0040": "Leeds Trinity",
 "0134": "King's College London",
 "0145": "St George's, UoL",
 "0190": "Norwich University of the Arts",
 "0211": "Leeds College of Art",
 "0108": "Aston",
 "0011": "Chester",
 "0170": "Aberdeen",
 "0204": "Manchester",
 "0101": "Royal Conservatoire of Scotland",
 "0155": "Nottingham",
 "0193": "Stranmillis UC",
 "0154": "Newcastle",
 "0178": "Bangor",
 "0203": "Buckingham",
 "0120": "Hull",
 "0090": "South Wales",
 "0033": "Royal Academy of Music",
 "0202": "London Met",
 "0012": "Canterbury Christ Church",
 "0039": "St Mary's, Twickenham",
 "0199": "Conservatoire for Dance and Drama",
 "0127": "Birkbeck",
 "0126": "Liverpool",
 "0188": "Institute of Cancer Research",
 "0059": "Greenwich",
 "0013": "York St John",
 "0176": "Trinity Saint David",
 "0208": "Guildhall School of Music and Drama",
 "0091": "Swansea Met",
 "0111": "Bradford",
 "0076": "London South Bank",
 "0210": "University Campus Suffolk",
 "0105": "West of Scotland",
 "0065": "Liverpool John Moores",
 "0197": "Arts University Bournemouth",
 "0109": "Bath",
 "0080": "West London",
 "0072": "Oxford Brookes",
 "0146": "SOAS",
 "0132": "Imperial College",
 "0035": "Royal Northern College of Music",
 "0053": "Central Lancashire",
 "0046": "Worcester",
 "9987": "Peninsula Medical School",
 "9998": "Hull York Medical School",
 "9999": "Brighton Sussex Medical School",
 "9988": "Manchester School of Architecture",
 "9989": "Kingston - St George's University",
 "9997": "Medway School of Pharmacy"
}