{"0126": [], "0125": ["BA (hons) American studies", "BA (hons) American studies (compulsory year abroad)", "BA (hons) English & American studies", "BA (hons) history & American studies"], "0021": ["BA (hons) American studies & history", "BA (hons) American studies & politics", "BA (hons) American studies & creative writing", "BA (hons) American studies & English language studies", "BA (hons) American studies & English", "BA (hons) American studies & film studies", "BA (hons) American studies & journalism studies", "BA (hons) American studies & media studies", "BA (hons) American studies & modern liberal arts", "BA (hons) American studies"], "0117": ["BA (hons) american history", "BA (hons) English & American literature", "BA (hons) American studies (compulsory year abroad)", "BA (hons) American studies (3 years) ", "BA (hons) American studies (foundation year)", "BA (hons) American literature with creative writing (compulsory year abroad)", "BA (hons) American & English literature (compulsory year abroad)", "BA (hons) film & American studies (compulsory year abroad)", "BA (hons) liberal arts", "BA (hons) liberal arts (foundation year)"], "0121": ["BA (hons) American studies & criminology", "BA (hons) American studies & English", "BA (hons) American studies & geography", "BA (hons) American studies & history", "BA (hons) American studies & international relations", "BA (hons) American studies & law", "BSc (hons) American studies & mathematics", "BA (hons) American studies & music", "BA (hons) American studies & music technology", "BA (hons) American studies & politics", "BSc (hons) American studies & psychology", "BA (hons) American studies & sociology", "BA (hons) American studies (foundation year)", "BA (hons) American studies major minor", "BA (hons) American studies", "BA (hons) English & American literature (foundation year)", "BA (hons) English & American literatures"], "0120": ["BA (hons) American studies (4 years) (compulsory year abroad)", "BA (hons) American studies (3 years) ", "BA (hons) American studies & English", "BA (hons) American studies & history", "BA (hons) American studies & film studies", "BA (hons) English & American literature & culture", "BA (hons) creative writing & American studies", "BA (hons) French & American studies (compulsory year abroad)", "BA (hons) German & American studies (compulsory year abroad)", "BA (hons) Spanish & American studies (compulsory year abroad)", "BA (hons) Italian & American studies (compulsory year abroad)", "BA (hons) philosophy & American studies"], "0163": ["BA (hons) history, literature & cultures of the americas (compulsory year abroad)"], "0162": ["LLB (hons) law with American studies (optional sandwich year)", "LLB (hons) law with American studies (compulsory year abroad)", "BA (hons) American studies (optional sandwich year) (compulsory year abroad)", "BA (hons) American studies & politics (compulsory year abroad)", "BA (hons) American studies & film studies (compulsory year abroad)", "BA (hons) American studies & English (compulsory year abroad)", "BA (hons) American studies & history (compulsory year abroad)", "BSc (hons) psychology with American studies (compulsory year abroad)"], "0118": ["BA (hons) criminology & American studies (compulsory year abroad)", "BA (hons) criminology & American studies", "BA (hons) English & united states literature (compulsory year abroad)", "BA (hons) Spanish studies with Latin American studies (compulsory year abroad)", "BA (hons) modern languages with Latin American studies (compulsory year abroad)", "BA (hons) Spanish, Portuguese & Brazilian studies (compulsory year abroad)", "BA (hons) American", "BA (hons) American (compulsory year abroad)", "BA (hons) Latin American studies (compulsory year abroad)", "BA (hons) English & united states literature", "BA (hons) Latin American studies with human rights (compulsory year abroad)", "BA (hons) Latin American studies with business management (compulsory year abroad)", "BA (hons) American", "BA (hons) American (compulsory year abroad)", "BA (hons) American history", "BA (hons) American history (compulsory year abroad)"], "0057": ["BA (hons) American studies & education studies (optional foundation year)", "BA (hons) American studies & English (optional foundation year)", "BA (hons) American studies & film & television studies (optional foundation year)", "BA (hons) American studies & geography (optional foundation year)", "BA (hons) American studies & geology (optional foundation year)", "BA (hons) American studies & human resource management (optional foundation year)", "BA (hons) American studies & history (optional foundation year)", "BA (hons) American studies & international relations & global development (optional foundation year)", "BA (hons) American studies & law (optional foundation year)", "BA (hons) American studies & marketing (optional foundation year)", "BA (hons) American studies & popular music production (optional foundation year)", "BA (hons) American studies & mathematics (optional foundation year)", "BA (hons) American studies & property development (optional foundation year)", "BA (hons) American studies & sport & exercise studies (optional foundation year)", "BA (hons) American studies & sociology (optional foundation year)", "BA (hons) American studies & theatre studies (optional foundation year)", "BA (hons) American studies & third world development (optional foundation year)", "BA (hons) early childhood studies & American studies (optional foundation year)", "BA (hons) professional writing & American studies (optional foundation year)", "BA (hons) American studies (optional foundation year)"], "0110": ["BA (hons) American & Canadian studies & history", "BA (hons) American & Canadian studies (with year abroad) ", "BA (hons) American & Canadian studies & history with a year abroad ", "BA (hons) anthropology & American studies", "BA (hons) American & Canadian studies & film studies", "BSc (hons) business & American studies", "BA (hons) American & Canadian studies", "BA (hons) American studies & English literature with year abroad", "BA (hons) American & Canadian studies & English literature"], "0122": ["BA (hons) American studies", "BA (hons) American studies (history) (compulsory year abroad)", "BA (hons) American studies (Latin America) (compulsory year abroad)", "BA (hons) American studies (literature) (compulsory year abroad)"], "0204": ["BA (hons) English literature & American studies", "BA (hons) history & American studies", "BA (hons) American studies", "BA (hons) Spanish, Portuguese & Latin American studies (optional sandwich year) (compulsory year abroad)"], "0155": ["BA (hons) American studies & Latin American studies", "BA (hons) American & English studies", "BA (hons) American & Canadian literature, history & culture", "BA (hons) American & Canadian literature, history & culture (international study) (compulsory year abroad)", "BA (hons) politics & American studies", "BA (hons) American studies & Latin American studies (compulsory year abroad)", "BA (hons) American studies & Latin American studies (beginners' Spanish) (compulsory year abroad)", "BA (hons) American studies & history", "BA (hons) film & television studies & American studies"], "0074": ["BA (hons) Spanish & Latin American studies", "BA (hons) American studies", "BA (hons) English & American studies", "BA (hons) American studies & history"], "0060": [], "0012": ["BA/BSc (hons) applied criminology with American studies", "BA/BSc (hons) applied criminology & American studies", "BA/BSc (hons) applied criminology & American studies (compulsory year abroad)", "BA/BSc (hons) applied criminology with American studies (compulsory year abroad)", "BA/BSc (hons) American studies with applied criminology", "BA/BSc (hons) American studies with applied criminology (compulsory year abroad)", "BA/BSc (hons) business computing with American studies", "BA/BSc (hons) business computing & American studies", "BA/BSc (hons) business computing with American studies (compulsory year abroad)", "BA/BSc (hons) business computing & American studies (compulsory year abroad)", "BA/BSc (hons) American studies with business computing", "BA/BSc (hons) American studies with business computing (compulsory year abroad)", "BA/BSc (hons) business studies with American studies", "BA/BSc (hons) business studies with American studies (compulsory year abroad)", "BA/BSc (hons) American studies with business studies", "BA/BSc (hons) American studies & business studies", "BA/BSc (hons) American studies & business studies (compulsory year abroad)", "BA/BSc (hons) American studies with business studies (compulsory year abroad)", "BA/BSc (hons) internet computing with American studies", "BA/BSc (hons) internet computing & American studies", "BA/BSc (hons) internet computing with American studies (compulsory year abroad)", "BA/BSc (hons) internet computing & American studies (compulsory year abroad)", "BA/BSc (hons) American studies with internet computing", "BA/BSc (hons) American studies with internet computing (compulsory year abroad)", "BA/BSc (hons) computing with American studies", "BA/BSc (hons) American studies & computing", "BA/BSc (hons) computing with American studies (compulsory year abroad)", "BA/BSc (hons) American studies with computing", "BA/BSc (hons) American studies & computing (compulsory year abroad)", "BA/BSc (hons) American studies with computing (compulsory year abroad)", "BA/BSc (hons) American studies with drama", "BA/BSc (hons) American studies with drama (compulsory year abroad)", "BA/BSc (hons) drama & American studies", "BA/BSc (hons) drama with American studies", "BA/BSc (hons) drama & American studies (compulsory year abroad)", "BA/BSc (hons) drama with American studies (compulsory year abroad)", "BA (hons) American studies with education studies", "BA (hons) American studies with education studies (compulsory year abroad)", "BA (hons) education studies with American studies", "BA (hons) education studies with American studies (compulsory year abroad)", "BA (hons) education studies & American studies (compulsory year abroad)", "BA (hons) education studies & American studies", "BA (hons) English language & communication & American studies", "BA (hons) English language & communication with American studies", "BA (hons) English language & communication & American studies (compulsory year abroad)", "BA (hons) English language & communication with American studies (compulsory year abroad)", "BA (hons) American studies with English language & communication", "BA (hons) American studies with English language & communication (compulsory year abroad)", "BA/BSc (hons) events management & American studies", "BA/BSc (hons) events management with American studies", "BA/BSc (hons) American studies with events management", "BA (hons) English literature with American studies", "BA (hons) English literature with American studies (compulsory year abroad)", "BA (hons) American studies with English literature", "BA (hons) American studies & English literature", "BA (hons) American studies & English literature (compulsory year abroad)", "BA (hons) American studies with English literature (compulsory year abroad)", "BA (hons) American studies with film radio & television studies", "BA (hons) American studies with film radio & television studies (compulsory year abroad)", "BA (hons) American studies & film radio & television studies", "BA (hons) American studies & film radio & TV (compulsory year abroad)", "BA (hons) film radio & television studies with American studies", "BA (hons) film radio & TV with American studies (compulsory year abroad)", "BA (hons) American studies with history", "BA (hons) American studies with history (compulsory year abroad)", "BA (hons) American studies & history", "BA (hons) American studies & history (compulsory year abroad)", "BA (hons) history with American studies", "BA (hons) history with American studies (compulsory year abroad)", "BA (hons) health studies with American studies", "BA (hons) health studies & American studies", "BA (hons) health studies & American studies (compulsory year abroad)", "BA (hons) health studies with American studies (compulsory year abroad)", "BA (hons) American studies with health studies (compulsory year abroad)", "BA (hons) media & communications with American studies", "BA (hons) media & communications with American studies (compulsory year abroad)", "BA (hons) American studies with media & communications", "BA (hons) American studies & media & communications", "BA (hons) American studies & media & communications (compulsory year abroad)", "BA (hons) American studies with media & communications (compulsory year abroad)", "BA/BSc (hons) marketing with American studies", "BA/BSc (hons) marketing with American studies (compulsory year abroad)", "BA/BSc (hons) American studies with marketing", "BA/BSc (hons) American studies & marketing", "BA/BSc (hons) American studies & marketing (compulsory year abroad)", "BA/BSc (hons) American studies with marketing (compulsory year abroad)", "BA/BSc (hons) sport & exercise science with American studies", "BA/BSc (hons) sport & exercise science with American studies (compulsory year abroad)", "BA/BSc (hons) American studies & sport & exercise science", "BA/BSc (hons) American studies with sport & exercise science", "BA/BSc (hons) American studies & sport & exercise science (compulsory year abroad)", "BA/BSc (hons) American studies with sport & exercise science (compulsory year abroad)", "BA/BSc (hons) tourism & leisure studies with American studies", "BA/BSc (hons) tourism & leisure studies with American studies (compulsory year abroad)", "BA/BSc (hons) American studies with tourism & leisure studies", "BA/BSc (hons) American studies & tourism & leisure studies", "BA/BSc (hons) American studies & tourism & leisure studies (compulsory year abroad)", "BA/BSc (hons) American studies with tourism & leisure studies (compulsory year abroad)", "BA (hons) American studies", "BA (hons) American studies", "BA (hons) American studies (compulsory year abroad)"], "0180": ["BA (hons) American studies & Welsh (a pathway for first language students) ", "BA (hons) American studies & history", "BA (hons) American studies & politics", "BA (hons) American studies", "BA (hons) English literature & American studies", "BA (hons) American studies & Welsh (a pathway for second language students) ", "BA (hons) American studies & English literature (compulsory year abroad)", "BA (hons) American studies & geography (compulsory year abroad)", "BA (hons) American studies & history (compulsory year abroad)", "BA (hons) American studies & politics (compulsory year abroad)", "BA (hons) American studies (compulsory year abroad)", "BA (hons) international relations & American studies (compulsory year abroad)", "LLB (hons) law & American studies", "LLB (hons) law & American studies (compulsory year abroad)"]}